odoo/addons/sale_order_invoice_amount/README.rst
odoo/addons/sale_order_invoice_amount/__init__.py
odoo/addons/sale_order_invoice_amount/__manifest__.py
odoo/addons/sale_order_invoice_amount/i18n/sale_order_invoice_amount.pot
odoo/addons/sale_order_invoice_amount/models/__init__.py
odoo/addons/sale_order_invoice_amount/models/sale_order.py
odoo/addons/sale_order_invoice_amount/readme/CONTRIBUTORS.rst
odoo/addons/sale_order_invoice_amount/readme/DESCRIPTION.rst
odoo/addons/sale_order_invoice_amount/static/description/icon.png
odoo/addons/sale_order_invoice_amount/static/description/index.html
odoo/addons/sale_order_invoice_amount/tests/__init__.py
odoo/addons/sale_order_invoice_amount/tests/test_sale_order_invoice_amount.py
odoo/addons/sale_order_invoice_amount/views/sale_order_view.xml
odoo13_addon_sale_order_invoice_amount-13.0.1.0.1.dist-info/METADATA
odoo13_addon_sale_order_invoice_amount-13.0.1.0.1.dist-info/WHEEL
odoo13_addon_sale_order_invoice_amount-13.0.1.0.1.dist-info/top_level.txt
odoo13_addon_sale_order_invoice_amount-13.0.1.0.1.dist-info/RECORD
